Metadata-Version: 1.0
Name: Stats-Distributions-Skyweldor
Version: 0.1
Summary: Gaussian and Binomial distributions
Home-page: UNKNOWN
Author: Skyweldor
Author-email: UNKNOWN
License: UNKNOWN
Platform: UNKNOWN
